heroku_py/__init__.py
heroku_py/authorization.py
heroku_py/constants.py
heroku_py/exceptions.py
heroku_py/heroku_client.py
heroku_py/utilities.py
heroku_py-1.2.0.dist-info/LICENSE
heroku_py-1.2.0.dist-info/METADATA
heroku_py-1.2.0.dist-info/WHEEL
heroku_py-1.2.0.dist-info/top_level.txt
heroku_py-1.2.0.dist-info/RECORD
