Metadata-Version: 2.1
Name: heroku-py
Version: 1.2.0
Summary: A Python3 wrapper around the v3 Heroku API.
Home-page: https://github.com/elfkuzco/heroku-py
Author: Orji Uchechukwu
Author-email: orjiuchechukwu52@yahoo.com
License: UNKNOWN
Keywords: Heroku,Heroku API
Platform: UNKNOWN
Classifier: Programming Language :: Python :: 3
Classifier: Programming Language :: Python :: 3.5
Classifier: Programming Language :: Python :: 3.6
Classifier: Programming Language :: Python :: 3.7
Classifier: Programming Language :: Python :: 3.8
Classifier: License :: OSI Approved :: MIT License
Classifier: Operating System :: OS Independent
Classifier: Intended Audience :: Developers
Requires-Python: >=3.5
License-File: LICENSE
Requires-Dist: requests (>=2.22.0)
